visionface/PyFaces.py
visionface/__init__.py
visionface/annotators/FaceAnnotators.py
visionface/annotators/base.py
visionface/annotators/detection.py
visionface/annotators/landmark.py
visionface/annotators/utils.py
visionface/annotators/helper/landmark_connections.py
visionface/annotators/helper/landmark_styles.py
visionface/commons/detection_utils.py
visionface/commons/download_files.py
visionface/commons/image_utils.py
visionface/commons/utils.py
visionface/db/qdrant_client.py
visionface/db/qdrant/collection_manager.py
visionface/db/qdrant/config.py
visionface/db/qdrant/data_manager.py
visionface/db/qdrant/search_manager.py
visionface/models/Detector.py
visionface/models/FaceEmbedding.py
visionface/models/LandmarkDetector.py
visionface/models/face_detection/MTCNN.py
visionface/models/face_detection/MediaPipe.py
visionface/models/face_detection/OpenCV.py
visionface/models/face_detection/YOLO.py
visionface/models/face_detection/YOLOEye.py
visionface/models/face_detection/YOLOWolrd.py
visionface/models/face_detection/mediapipe.py
visionface/models/face_embedding/ArcFace.py
visionface/models/face_embedding/Dlib.py
visionface/models/face_embedding/FaceNet.py
visionface/models/landmark_detection/Dlib.py
visionface/models/landmark_detection/MediaPipeLandmark.py
visionface/models/landmark_detection/utils.py
visionface/modules/detection.py
visionface/modules/embedding.py
visionface/modules/landmarks.py
visionface/modules/modeling.py
visionface/modules/recognition.py
visionface-1.0.0.dist-info/licenses/LICENSE
visionface-1.0.0.dist-info/METADATA
visionface-1.0.0.dist-info/WHEEL
visionface-1.0.0.dist-info/entry_points.txt
visionface-1.0.0.dist-info/top_level.txt
visionface-1.0.0.dist-info/RECORD
