Metadata-Version: 2.4
Name: visionface
Version: 1.0.0
Summary: Modern face detection, recognition & analysis framework with 12+ models
Home-page: https://github.com/miladfa7/visionface
Author: VisionFace Team
Author-email: visio.face2025@gmail.com
License: MIT
Project-URL: Documentation, https://visionface.readthedocs.io
Project-URL: Source Code, https://github.com/miladfa7/visionface
Project-URL: Bug Tracker, https://github.com/miladfa7/visionface/issues
Project-URL: Changelog, https://github.com/miladfa7/visionface/blob/main/CHANGELOG.md
Keywords: computer-vision,face-detection,face-recognition,facial-landmarks,deep-learning,pytorch,yolo,mediapipe,artificial-intelligence,biometrics,image-processing,real-time,production-ready
Platform: any
Classifier: Development Status :: 4 - Beta
Classifier: Intended Audience :: Developers
Classifier: Intended Audience :: Science/Research
Classifier: Intended Audience :: Education
Classifier: License :: OSI Approved :: MIT License
Classifier: Operating System :: OS Independent
Classifier: Programming Language :: Python :: 3
Classifier: Programming Language :: Python :: 3.8
Classifier: Programming Language :: Python :: 3.9
Classifier: Programming Language :: Python :: 3.10
Classifier: Programming Language :: Python :: 3.11
Classifier: Programming Language :: Python :: 3.12
Classifier: Programming Language :: Python :: 3.13
Classifier: Topic :: Scientific/Engineering :: Artificial Intelligence
Classifier: Topic :: Scientific/Engineering :: Image Recognition
Classifier: Topic :: Software Development :: Libraries :: Python Modules
Classifier: Topic :: Multimedia :: Graphics :: Graphics Conversion
Classifier: Topic :: Security
Classifier: Framework :: FastAPI
Requires-Python: >=3.8
License-File: LICENSE
Requires-Dist: torch>=1.8.0
Requires-Dist: torchvision>=0.9.0
Requires-Dist: numpy>=1.19.0
Requires-Dist: opencv-python>=4.5.0
Requires-Dist: Pillow>=8.0.0
Requires-Dist: requests>=2.25.0
Dynamic: author
Dynamic: author-email
Dynamic: classifier
Dynamic: description
Dynamic: description-content-type
Dynamic: home-page
Dynamic: keywords
Dynamic: license
Dynamic: license-file
Dynamic: platform
Dynamic: project-url
Dynamic: requires-dist
Dynamic: requires-python
Dynamic: summary
